LICENSE
MANIFEST.in
README.md
setup.py
django_deploy/__init__.py
django_deploy/deploy.py
django_deploy/models.py
django_deploy/setup.py
django_deploy/management/__init__.py
django_deploy/management/commands/__init__.py
django_deploy/management/commands/deploy.py
django_deploy_setup.egg-info/PKG-INFO
django_deploy_setup.egg-info/SOURCES.txt
django_deploy_setup.egg-info/dependency_links.txt
django_deploy_setup.egg-info/requires.txt
django_deploy_setup.egg-info/top_level.txt