Metadata-Version: 1.0
Name: django-deploy-setup
Version: 0.1a
Summary: Deployment tools for django projects
Home-page: https://github.com/elvard/django-deploy
Author: Tomáš Ehrlich
Author-email: tomas.ehrlich@gmail.com
License: MIT
Platform: UNKNOWN
